SFvdriftPy/__init__.py
SFvdriftPy/model.py
SFvdriftPy-0.1.2.dist-info/METADATA
SFvdriftPy-0.1.2.dist-info/WHEEL
SFvdriftPy-0.1.2.dist-info/top_level.txt
SFvdriftPy-0.1.2.dist-info/RECORD
