Metadata-Version: 2.1
Name: SFvdriftPy
Version: 0.1.2
Summary: Model for equatorial vertical drift based on paper published by Scherliess & Fejer.
Home-page: https://github.com/mcardonaserrano/SFvdriftPy
Author: Mateo Cardona Serrano (them)
Author-email: mcardonaserrano@berkeley.edu
Classifier: Programming Language :: Python :: 3
Classifier: License :: OSI Approved :: MIT License
Classifier: Operating System :: OS Independent
Requires-Python: >=3.6
Requires-Dist: numpy
